patterna/__init__.py
patterna/matcher.py
patterna/patterns.py
patterna-0.1.0.dev1.dist-info/METADATA
patterna-0.1.0.dev1.dist-info/WHEEL
patterna-0.1.0.dev1.dist-info/licenses/LICENSE
patterna-0.1.0.dev1.dist-info/RECORD
