Metadata-Version: 2.4
Name: patterna
Version: 0.1.0.dev1
Summary: Pure Python library for simple pattern matching on dicts, lists, tuples, and objects. Inspired by Python 3.10 match/case, portable to Python 3.7+.
Author-email: Saadman Rafat <saadman@outlook.com>
License-Expression: MIT
License-File: LICENSE
Keywords: pattern matching,python,structural pattern matching
Classifier: Development Status :: 4 - Beta
Classifier: Intended Audience :: Developers
Classifier: License :: OSI Approved :: MIT License
Classifier: Programming Language :: Python
Classifier: Programming Language :: Python :: 3
Classifier: Programming Language :: Python :: 3.7
Classifier: Programming Language :: Python :: 3.8
Classifier: Programming Language :: Python :: 3.9
Classifier: Programming Language :: Python :: 3.10
Classifier: Programming Language :: Python :: 3.11
Classifier: Programming Language :: Python :: 3.12
Classifier: Topic :: Software Development :: Libraries
Classifier: Topic :: Utilities
Requires-Python: >=3.7
